<?xml version="1.0" encoding="utf-8" ?>
<status>
    <starttime utc="1623914840">20210617 15:27:00</starttime>
    <!-- duration is in seconds -->
    <duration>11</duration>
    <!-- time is in seconds -->
    <elapsed_time>18392</elapsed_time>
    <recording meeting_type="1" random_id="1293675190">true</recording>
    <title>实时会议</title>
    <last_token_holder>1</last_token_holder>
    <!-- how the meeting is terminated. 0: empty room; 1: owner's request; 2: timer is over; 3: server shutdown; 4: other reason; 5: out of memory; 6: by admin -->
    <how>0</how>
    <participant userid="1" name="Administrator" />
</status>
